nosplash/__main__.py
nosplash/nosplash.py
nosplash-0.3.0.data/scripts/nosplash.py
nosplash-0.3.0.dist-info/LICENSE
nosplash-0.3.0.dist-info/METADATA
nosplash-0.3.0.dist-info/WHEEL
nosplash-0.3.0.dist-info/top_level.txt
nosplash-0.3.0.dist-info/RECORD
