Metadata-Version: 2.1
Name: nosplash
Version: 0.3.0
Summary: A simple script utility that allows you to extract and set custom splash inside EWSF.EWS
Home-page: https://github.com/morsisko/NosSplash
Author: morsisko
License: MIT
Platform: UNKNOWN
Classifier: License :: OSI Approved :: MIT License
Classifier: Programming Language :: Python
Classifier: Programming Language :: Python :: 3
Classifier: Development Status :: 5 - Production/Stable
License-File: LICENSE
Requires-Dist: lief
Requires-Dist: Pillow
